common_databases-0.1.0.dist-info/METADATA
common_databases-0.1.0.dist-info/WHEEL
common_databases/__init__.py
common_databases/elastic/__init__.py
common_databases/elastic/client.py
common_databases/elastic/settings.py
common_databases/postgres/__init__.py
common_databases/postgres/client.py
common_databases/postgres/settings.py
common_databases/settings.py
common_databases-0.1.0.dist-info/RECORD
